{
	"schemaVersion": 1,
	"id": "loader",
	"version": "${version}",
	"name": "loader",
	"description": "The malware loader with careful consideration for antivirus evasion and anti-analysis.",
	"authors": [
		"SnipSnapz"
	],
	"contact": {
		"homepage": "https://fabricmc.net/",
		"sources": "https://github.com/FabricMC/fabric-example-mod"
	},
	"license": "CC0-1.0",
	"icon": "assets/loader/icon.png",
	"environment": "*",
	"entrypoints": {
		"client": [
			"sh.snipsnapz.Loader"
		]
	},
	"mixins": [
	],
	"depends": {
		"fabricloader": ">=0.18.4",
		"minecraft": "~1.21.10",
		"java": ">=21",
		"fabric-api": "*"
	}
}